fiberpy/__about__.py
fiberpy/__init__.py
fiberpy/closure.py
fiberpy/interface.py
fiberpy/mechanics.py
fiberpy/orientation.py
fiberpy/tensor.py
fiberpy-0.2.0.dist-info/licenses/LICENSE
fiberpy-0.2.0.dist-info/METADATA
fiberpy-0.2.0.dist-info/WHEEL
fiberpy-0.2.0.dist-info/top_level.txt
fiberpy-0.2.0.dist-info/RECORD
