Metadata-Version: 2.4
Name: fiberpy
Version: 0.2.0
Summary: Computional methods for fiber-reinforced composites
Author-email: Tianyi Li <tianyikillua@gmail.com>
Project-URL: Homepage, https://github.com/tianyikillua/fiberpy
Classifier: Development Status :: 5 - Production/Stable
Classifier: Intended Audience :: Science/Research
Classifier: Operating System :: OS Independent
Classifier: Programming Language :: Python :: 3
Requires-Python: >=3.12
License-File: LICENSE
Requires-Dist: numpy
Requires-Dist: scipy
Provides-Extra: dev
Requires-Dist: pytest; extra == "dev"
Requires-Dist: matplotlib; extra == "dev"
Dynamic: license-file
